README.md
setup.py
prueba_servidor_calculadora/calculadora.py
prueba_servidor_calculadora.egg-info/PKG-INFO
prueba_servidor_calculadora.egg-info/SOURCES.txt
prueba_servidor_calculadora.egg-info/dependency_links.txt
prueba_servidor_calculadora.egg-info/entry_points.txt
prueba_servidor_calculadora.egg-info/requires.txt
prueba_servidor_calculadora.egg-info/top_level.txt